[
    {
        "id": 0,
        "name": "categories",
        "active": false,
        "imgList": [
            {
                "id": 0,
                "img": "images/plp/icon_crossbody.png",
                "added": false
            },
            {
                "id": 1,
                "img": "images/plp/icon_shoulder.png",
                "added": false
            },
            {
                "id": 2,
                "img": "images/plp/icon_backpacks.png",
                "added": false
            },
            {
                "id": 3,
                "img": "images/plp/icon_totes.png",
                "added": false
            },
            {
                "id": 4,
                "img": "images/plp/icon_baby_bags.png",
                "added": false
            }
        ]
    },
    {
        "id": 1,
        "name": "colors",
        "active": false,
        "imgList": [
            {
                "id": 0,
                "img": "images/plp/icon_crossbody.png",
                "added": false
            },
            {
                "id": 1,
                "img": "images/plp/icon_shoulder.png",
                "added": false
            },
            {
                "id": 2,
                "img": "images/plp/icon_backpacks.png",
                "added": false
            },
            {
                "id": 3,
                "img": "images/plp/icon_totes.png",
                "added": false
            },
            {
                "id": 4,
                "img": "images/plp/icon_baby_bags.png",
                "added": false
            }
        ]
    },
    {
        "id": 2,
        "name": "patterns",
        "active": false,
        "imgList": [
            {
                "id": 0,
                "img": "images/plp/icon_crossbody.png",
                "added": false
            },
            {
                "id": 1,
                "img": "images/plp/icon_shoulder.png",
                "added": false
            },
            {
                "id": 2,
                "img": "images/plp/icon_backpacks.png",
                "added": false
            },
            {
                "id": 3,
                "img": "images/plp/icon_totes.png",
                "added": false
            },
            {
                "id": 4,
                "img": "images/plp/icon_baby_bags.png",
                "added": false
            }
        ]
    },
    {
        "id": 3,
        "name": "materials",
        "active": false,
        "imgList": [
            {
                "id": 0,
                "img": "images/plp/icon_crossbody.png",
                "added": false
            },
            {
                "id": 1,
                "img": "images/plp/icon_shoulder.png",
                "added": false
            },
            {
                "id": 2,
                "img": "images/plp/icon_backpacks.png",
                "added": false
            },
            {
                "id": 3,
                "img": "images/plp/icon_totes.png",
                "added": false
            },
            {
                "id": 4,
                "img": "images/plp/icon_baby_bags.png",
                "added": false
            }
        ]
    },
    {
        "id": 4,
        "name": "occasion",
        "active": false,
        "imgList": [
            {
                "id": 0,
                "img": "images/plp/51.png",
                "added": false
            },
            {
                "id": 1,
                "img": "images/plp/52.png",
                "added": false
            },
            {
                "id": 2,
                "img": "images/plp/53.png",
                "added": false
            },
            {
                "id": 3,
                "img": "images/plp/54.png",
                "added": false
            }
        ]
    },
    {
        "id": 5,
        "name": "what's inside",
        "active": false,
        "imgList": [
            {
                "id": 0,
                "img": "images/plp/61.jpg",
                "added": false
            },
            {
                "id": 1,
                "img": "images/plp/62.jpg",
                "added": false
            },
            {
                "id": 2,
                "img": "images/plp/63.jpg",
                "added": false
            }
        ]
    },
    {
        "id": 6,
        "name": "fans say",
        "active": false,
        "imgList": [
            {
                "id": 0,
                "img": "images/plp/71.jpg",
                "added": false
            },
            {
                "id": 1,
                "img": "images/plp/72.jpg",
                "added": false
            },
            {
                "id": 2,
                "img": "images/plp/73.jpg",
                "added": false
            }
        ]
    }
]